{
    "sections": [
        {
            "spacing": 30,
            "items": [
                {
                    "id": "GSPagerItem",
                    "spacing": 30.0,
                    "items": [
                        {
                            "id": "TestHItem",
                            "title": "Hello world"
                        },
                        {
                            "id": "TestHItem",
                            "title": "Hello world"
                        }
                    ]
                }
            ]
        }
    ]
}
