{
    "sections": [
        {
            "spacing": 30,
            "items": [
                {
                    "id": "BaseTestItem",
                    "title": "This ia test"
                },
                {
                    "id": "TestItem2",
                    "title": "This ia tefgf gfgfggfgst"
                },
                {
                    "id": "BaseTestItem",
                    "title": "This ia test"
                },
                {
                    "id": "BaseTestItem",
                    "title": "This ia test"
                }
            ]
        }
    ]
}
